{"width":1024,"imagePath":"Слизь2_tex.png","SubTexture":[{"width":923,"y":1,"height":108,"name":"СЛИЗЬ лвл2/Layer3","x":1},{"width":91,"y":424,"height":78,"name":"СЛИЗЬ лвл2/Layer9","x":1},{"width":77,"y":348,"height":63,"name":"СЛИЗЬ лвл2/Layer16","x":154},{"width":39,"y":246,"height":93,"name":"СЛИЗЬ лвл2/痼赅","x":208},{"width":118,"y":424,"height":53,"name":"СЛИЗЬ лвл2/Layer11","x":94},{"width":47,"y":246,"height":40,"name":"СЛИЗЬ лвл2/Layer12","x":249},{"width":151,"y":111,"height":311,"name":"СЛИЗЬ лвл2/Layer2","x":1},{"width":112,"y":111,"height":133,"name":"СЛИЗЬ лвл2/Layer6","x":154},{"frameWidth":122,"y":1,"frameHeight":132,"width":95,"frameX":-11,"height":121,"name":"СЛИЗЬ лвл2/Layer10","frameY":-10,"x":926},{"frameWidth":67,"y":246,"frameHeight":105,"width":52,"frameX":-7,"height":100,"name":"СЛИЗЬ лвл2/Layer13","frameY":-5,"x":154},{"width":118,"y":424,"height":53,"name":"СЛИЗЬ лвл2/Layer14","x":214},{"width":47,"y":341,"height":40,"name":"СЛИЗЬ лвл2/Layer15","x":233}],"height":512,"name":"Слизь2"}